<?xml version="1.0" encoding="UTF-8"?>
<Tokens version="1.0">
	<File path="Classes/ALOCRScanViewPlugin.html">
		
		<Token>
			<TokenIdentifier>//apple_ref/occ/cl/ALOCRScanViewPlugin</TokenIdentifier>
			<Abstract type="html"></Abstract>
			<DeclaredIn>ALOCRScanViewPlugin.h</DeclaredIn>
            
			
			<NodeRef refid="36"/>
		</Token>
		
		
		<Token>
			<TokenIdentifier>//apple_ref/occ/instm/ALOCRScanViewPlugin/setOcrScanPlugin:</TokenIdentifier>
			<Abstract type="html"></Abstract>
			<DeclaredIn>ALOCRScanViewPlugin.h</DeclaredIn>
			
			<Declaration>@property (nullable, nonatomic, strong) ALOCRScanPlugin *ocrScanPlugin</Declaration>
			
			
			<Anchor>//api/name/ocrScanPlugin</Anchor>
            <NodeRef refid="36"/>
		</Token>
		
		<Token>
			<TokenIdentifier>//apple_ref/occ/instm/ALOCRScanViewPlugin/ocrScanPlugin</TokenIdentifier>
			<Abstract type="html"></Abstract>
			<DeclaredIn>ALOCRScanViewPlugin.h</DeclaredIn>
			
			<Declaration>@property (nullable, nonatomic, strong) ALOCRScanPlugin *ocrScanPlugin</Declaration>
			
			
			<Anchor>//api/name/ocrScanPlugin</Anchor>
            <NodeRef refid="36"/>
		</Token>
		
		<Token>
			<TokenIdentifier>//apple_ref/occ/instp/ALOCRScanViewPlugin/ocrScanPlugin</TokenIdentifier>
			<Abstract type="html"></Abstract>
			<DeclaredIn>ALOCRScanViewPlugin.h</DeclaredIn>
			
			<Declaration>@property (nullable, nonatomic, strong) ALOCRScanPlugin *ocrScanPlugin</Declaration>
			
			
			<Anchor>//api/name/ocrScanPlugin</Anchor>
            <NodeRef refid="36"/>
		</Token>
		
		<Token>
			<TokenIdentifier>//apple_ref/occ/instm/ALOCRScanViewPlugin/initWithFrame:scanPlugin:</TokenIdentifier>
			<Abstract type="html"></Abstract>
			<DeclaredIn>ALOCRScanViewPlugin.h</DeclaredIn>
			
			<Declaration>- (_Nullable instancetype)initWithFrame:(CGRect)frame scanPlugin:(ALOCRScanPlugin *_Nonnull)ocrScanPlugin</Declaration>
			
			
			<Anchor>//api/name/initWithFrame:scanPlugin:</Anchor>
            <NodeRef refid="36"/>
		</Token>
		
        
        
	</File>
</Tokens>